tinysync/__init__.py
tinysync/backendMethods.py
tinysync/config.py
tinysync/dicttable.py
tinysync/log.py
tinysync/syncer.py
tinysync/utils.py
tinysync/backend/__init__.py
tinysync/backend/abc.py
tinysync/backend/ftp.py
tinysync/backend/localFS.py
tinysync/backend/nixssh.py
tinysync/backend/rclone.py
tinysync/backend/webdav.py
tinysync-0.0.21.dist-info/METADATA
tinysync-0.0.21.dist-info/WHEEL
tinysync-0.0.21.dist-info/top_level.txt
tinysync-0.0.21.dist-info/RECORD
