Metadata-Version: 2.4
Name: tinysync
Version: 0.0.21
Summary: TinySync is a two-path (bi-direction) synchronization algorithm implemented in pure Python that can synchronize files between any two kinds of backends.
Home-page: https://github.com/HengyueLi/tinysync
License: LICENSE.md
Requires-Python: >=3.7
Dynamic: description
Dynamic: description-content-type
Dynamic: home-page
Dynamic: license
Dynamic: requires-python
Dynamic: summary
